northstar_epe_planner/__init__.py
northstar_epe_planner/northstar.py
northstar_epe_planner-0.0.2.dist-info/LICENSE
northstar_epe_planner-0.0.2.dist-info/METADATA
northstar_epe_planner-0.0.2.dist-info/WHEEL
northstar_epe_planner-0.0.2.dist-info/top_level.txt
northstar_epe_planner-0.0.2.dist-info/RECORD
