Metadata-Version: 2.1
Name: northstar-epe-planner
Version: 0.0.2
Summary: Package to help interact with Northstar's EPE Planner
License: UNKNOWN
Platform: UNKNOWN
License-File: LICENSE
